{"id":141429,"uri":"https://dadosabertos.camara.leg.br/api/v2/proposicoes/141429","siglaTipo":"EMP","idTipo":131,"numero":13,"ano":2003,"ementa":"Autoriza o Poder Executivo a criar a empresa pública denominada Empresa Brasileira de Hemoderivados e Biotecnologia - HEMOBRÁS, e dá outras providências. ","dataApresentacao":"2003-11-06T19:04","uriOrgaoNumerador":null,"uriUltimoRelator":null,"statusProposicao":{"dataHora":null,"sequencia":null,"siglaOrgao":null,"uriOrgao":"https://dadosabertos.camara.leg.br/api/v2/orgaos/null","regime":".","descricaoTramitacao":null,"idTipoTramitacao":null,"descricaoSituacao":null,"idSituacao":null,"despacho":"","url":"http://www.camara.gov.br/proposicoesWeb/prop_mostrarintegra?codteor=178694"},"tipoAutor":"Deputado","idTipoAutor":10000,"uriAutores":"https://dadosabertos.camara.leg.br/api/v2/deputados/74553","descricaoTipo":"Emenda de Plenário","ementaDetalhada":null,"keywords":null,"uriPropPrincipal":null,"uriPropAnterior":null,"uriPropPosterior":null,"urlInteiroTeor":"http://www.camara.gov.br/proposicoesWeb/prop_mostrarintegra?codteor=178694","urnFinal":null,"texto":null,"justificativa":null}